ktechpayapi/__init__.py
ktechpayapi/base.py
ktechpayapi/ktechpay.py
ktechpayapi/transaction.py
ktechpayapi-1.4.0.dist-info/LICENSE
ktechpayapi-1.4.0.dist-info/METADATA
ktechpayapi-1.4.0.dist-info/WHEEL
ktechpayapi-1.4.0.dist-info/top_level.txt
ktechpayapi-1.4.0.dist-info/RECORD
